django_live_dashboard/__init__.py
django_live_dashboard/apps.py
django_live_dashboard/default_settings.py
django_live_dashboard/lifespan.py
django_live_dashboard/middleware.py
django_live_dashboard/models.py
django_live_dashboard/serializer.py
django_live_dashboard/static/.gitkeep
django_live_dashboard/static/django_live_dashboard/index.css
django_live_dashboard/static/django_live_dashboard/index.js
django_live_dashboard/static/django_live_dashboard/vendor.js
django_live_dashboard/static/django_live_dashboard/vendor.js.LICENSE.txt
django_live_dashboard/templates/django_live_dashboard/base.html
django_live_dashboard/urls.py
django_live_dashboard/views.py
django_live_dashboard/websocket.py
django_live_dashboard/worker.py
django_live_dashboard-0.0.4.dist-info/WHEEL
django_live_dashboard-0.0.4.dist-info/METADATA
django_live_dashboard-0.0.4.dist-info/RECORD
