Metadata-Version: 2.1
Name: django-live-dashboard
Version: 0.0.4
Summary: Live runtime metrics dashboard for Django
License: MIT
Author: shen
Author-email: dustet@gmail.com
Requires-Python: >3.6,<4
Classifier: License :: OSI Approved :: MIT License
Classifier: Programming Language :: Python :: 3
Classifier: Programming Language :: Python :: 3.7
Classifier: Programming Language :: Python :: 3.8
Requires-Dist: aredis (>=1.1.8,<2.0.0)
Requires-Dist: pydantic (>=1.6.1,<2.0.0)
Requires-Dist: redis (>=3.5.3,<4.0.0)
